README.md
setup.cfg
setup.py
intvalpy_test/RealInterval.py
intvalpy_test/__init__.py
intvalpy_test/intoper.py
intvalpy_test/visualization.py
intvalpy_test.egg-info/PKG-INFO
intvalpy_test.egg-info/SOURCES.txt
intvalpy_test.egg-info/dependency_links.txt
intvalpy_test.egg-info/requires.txt
intvalpy_test.egg-info/top_level.txt
intvalpy_test/linear/__init__.py
intvalpy_test/linear/overdetermined.py
intvalpy_test/linear/square_system.py
intvalpy_test/linear/system_properties.py
intvalpy_test/nonlinear/__init__.py
intvalpy_test/nonlinear/external_evaluation.py
intvalpy_test/nonlinear/optimize.py
intvalpy_test/nonlinear/solution_existence.py