Metadata-Version: 2.1
Name: intvalpy-test
Version: 0.0.12
Summary: An interval library in Python that uses classical interval arithmetic and Kauher arithmetic + Kahan division in some functions
Home-page: https://github.com/AndrosovAS/intvalpy
Author: Андросов Артем Станиславович
Author-email: artem.androsov@gmail.com
License: MIT License
Keywords: Interval,inequality visualization,optimal solutions,math,range
Platform: UNKNOWN
